[
  {
    "name": "Dechant",
    "appellationName": "Kamptal DAC",
    "regionName": "Lower Austria",
    "classification": "erste_lage"
  },
  {
    "name": "Loiserberg",
    "appellationName": "Kamptal DAC",
    "regionName": "Lower Austria",
    "classification": "erste_lage"
  },
  {
    "name": "Spiegel",
    "appellationName": "Kamptal DAC",
    "regionName": "Lower Austria",
    "classification": "erste_lage"
  },
  {
    "name": "Seeberg",
    "appellationName": "Kamptal DAC",
    "regionName": "Lower Austria",
    "classification": "erste_lage"
  },
  {
    "name": "Kittmannsberg",
    "appellationName": "Kamptal DAC",
    "regionName": "Lower Austria",
    "classification": "erste_lage"
  },
  {
    "name": "Steinhaus",
    "appellationName": "Kamptal DAC",
    "regionName": "Lower Austria",
    "classification": "erste_lage"
  },
  {
    "name": "Steinmassl",
    "appellationName": "Kamptal DAC",
    "regionName": "Lower Austria",
    "classification": "erste_lage"
  },
  {
    "name": "Thal",
    "appellationName": "Kamptal DAC",
    "regionName": "Lower Austria",
    "classification": "erste_lage"
  },
  {
    "name": "Schenkenbichl",
    "appellationName": "Kamptal DAC",
    "regionName": "Lower Austria",
    "classification": "erste_lage"
  },
  {
    "name": "Käferberg",
    "appellationName": "Kamptal DAC",
    "regionName": "Lower Austria",
    "classification": "erste_lage"
  },
  {
    "name": "Gaisberg",
    "appellationName": "Kamptal DAC",
    "regionName": "Lower Austria",
    "classification": "erste_lage"
  },
  {
    "name": "Heiligenstein",
    "appellationName": "Kamptal DAC",
    "regionName": "Lower Austria",
    "classification": "erste_lage"
  },
  {
    "name": "Kogelberg",
    "appellationName": "Kamptal DAC",
    "regionName": "Lower Austria",
    "classification": "erste_lage"
  },
  {
    "name": "Grub",
    "appellationName": "Kamptal DAC",
    "regionName": "Lower Austria",
    "classification": "erste_lage"
  },
  {
    "name": "Lamm",
    "appellationName": "Kamptal DAC",
    "regionName": "Lower Austria",
    "classification": "erste_lage"
  },
  {
    "name": "Renner",
    "appellationName": "Kamptal DAC",
    "regionName": "Lower Austria",
    "classification": "erste_lage"
  },
  {
    "name": "Offenberg",
    "appellationName": "Kamptal DAC",
    "regionName": "Lower Austria",
    "classification": "erste_lage"
  },
  {
    "name": "Wechselberg Spiegel",
    "appellationName": "Kamptal DAC",
    "regionName": "Lower Austria",
    "classification": "erste_lage"
  },
  {
    "name": "Berg Vogelsang",
    "appellationName": "Kamptal DAC",
    "regionName": "Lower Austria",
    "classification": "erste_lage"
  }
]
